{
  "0400": "Int'l Correspondence School",
  "0401": "Asian Development Bank",
  "0410": "Radio Bible Class",
  "0420": "Bible Church on the Air",
  "0550": "Feblas Col. of Bible",
  "0560": "Far Eastern Broadcasting",
  "1000": "Manila CPO - Ermita",
  "1001": "Quiapo",
  "1002": "Intramuros",
  "1003": "Sta. Cruz South",
  "1004": "Malate",
  "1005": "San Miguel",
  "1006": "Binondo",
  "1007": "Paco",
  "1008": "Sampaloc East",
  "1009": "Sta. Ana",
  "1010": "San Nicolas",
  "1011": "Pandacan",
  "1012": "Tondo South",
  "1013": "Tondo North",
  "1014": "Sta. Cruz North",
  "1015": "Sampaloc West",
  "1016": "Sta. Mesa",
  "1017": "San Andres Bukid",
  "1018": "Port Area (South)",
  "1100": [
    "Central",
    "Piñahan",
    "Project 6",
    "Quezon City CPO"
  ],
  "1101": [
    "Botocan",
    "Diliman",
    "Krus na Ligas",
    "Malaya",
    "Old Capitol Site",
    "San Vicente",
    "Sikatuna Village",
    "Teachers Village",
    "University of the Philippines",
    "UP Village"
  ],
  "1102": [
    "Amihan",
    "Claro",
    "Duyan-Duyan",
    "E. Rodriguez",
    "Kamias",
    "Quirino District/Project 2 & 3",
    "Silangan"
  ],
  "1103": [
    "Kamuning",
    "Laging Handa",
    "Obrero",
    "Paligsahan",
    "Roxas District",
    "Sacred Heart",
    "South Triangle"
  ],
  "1104": [
    "Damayan",
    "Mariblo",
    "Nayon Kaunlaran",
    "Paraiso",
    "Phil-Am / Philam",
    "Santa Cruz",
    "Talayan",
    "West Triangle"
  ],
  "1105": [
    "Alicia",
    "Bagong Pag-asa",
    "Bungad",
    "Del Monte",
    "Katipunan",
    "Masambong",
    "Paltok",
    "Project 7",
    "Ramon Magsaysay",
    "San Antonio",
    "Sto. Cristo",
    "Veterans Village"
  ],
  "1106": [
    "Apolonio Samson",
    "Baesa",
    "Bahay Toro",
    "Balintawak",
    "Balumbato",
    "Project 8",
    "Unang Sigaw"
  ],
  "1107": [
    "New Era",
    "Pasong Tamo"
  ],
  "1108": [
    "Loyola Heights",
    "Pansol"
  ],
  "1109": [
    "Bagong Buhay",
    "Bayanihan",
    "Blue Ridge",
    "Cubao",
    "Dioquino Zobel",
    "Escopa",
    "Mangga",
    "Marilag",
    "Masagana",
    "Milagrosa",
    "Project 4",
    "San Roque",
    "Socorro",
    "Tagumpay",
    "Villa Maria Clara"
  ],
  "1110": [
    "Bagong bayan",
    "Camp Aguinaldo",
    "Libis",
    "St. Ignatius",
    "Talampas",
    "Ugong Norte",
    "White Plains"
  ],
  "1111": [
    "Bagong Lipunan",
    "Crame",
    "Immaculate Conception",
    "Kaunlaran",
    "Pinagkaisahan",
    "San Martin de Porres"
  ],
  "1112": [
    "Damayan Lagi",
    "Horseshoe",
    "Kalusugan",
    "Kristong Hari",
    "Mariana",
    "Valencia"
  ],
  "1113": [
    "Don Manuel",
    "Dona Aurora",
    "Doña Imelda",
    "Dona Josefa",
    "San Isidro",
    "Santol",
    "Santo Nino",
    "Tatalon"
  ],
  "1114": [
    "Gintong Silahis",
    "La Loma",
    "Lourdes",
    "Maharlica",
    "Matalahib",
    "Parang Bundok",
    "St. Peter",
    "Salvacion",
    "San Isidro Labrador",
    "Santa Teresita",
    "Sienna"
  ],
  "1115": [
    "Balingasa",
    "Damar",
    "Manresa",
    "Pag-Ibig sa Nayon",
    "San Jose"
  ],
  "1116": [
    "Bagbag",
    "San Bartolome",
    "Sangandaan",
    "Sauyo",
    "Talipapa",
    "Tandang Sora"
  ],
  "1117": [
    "Capri",
    "Gulod",
    "San Agustin",
    "Santa Lucia",
    "Santa Monica"
  ],
  "1118": [
    "Fairview",
    "Pasong Putik"
  ],
  "1119": [
    "Bagong Silangan",
    "Matandang Balara",
    "Payatas"
  ],
  "1120": [
    "BF Homes",
    "Violago Homes"
  ],
  "1121": [
    "Commonwealth",
    "Fairview North"
  ],
  "1122": "Fairview South",
  "1123": [
    "Damong Maliit",
    "Novaliches Town Proper"
  ],
  "1124": "Kaligayahan",
  "1125": [
    "Dona Faustina Subd.",
    "Nagkaisang Nayaon"
  ],
  "1126": [
    "Batasan Hills",
    "Capitol Hills/Park"
  ],
  "1127": "Holy Spirit",
  "1128": [
    "Culiat",
    "Vasra"
  ],
  "1200": "Makati CPO + Buendia Ave",
  "1201": "Fort Bonifacio (Camp)",
  "1202": "Fort Bonifacio Naval Stn.",
  "1203": "San Antonio Village",
  "1204": "La Paz-Singkamas-Tejeros",
  "1205": "Sta. Cruz",
  "1206": "Kasilawan",
  "1207": "Olympia & Carmona",
  "1208": "Valenzuela, Santiago, Rizal",
  "1209": "Bel-air",
  "1210": "Poblacion",
  "1211": "Guadalupe Viejo",
  "1212": "Guadalupe Nuevo",
  "1213": "Pinagkaisahan-Pitogo",
  "1214": "Cembo",
  "1215": "Rembo (West)",
  "1216": "Rembo (East)",
  "1217": "Comembo",
  "1218": "Pembo",
  "1219": "Forbes Park North",
  "1220": "Forbes Park South",
  "1221": "Dasmarinas Village North",
  "1222": "Dasmarinas Village South",
  "1223": "San Lorenzo Village",
  "1224": "Makati Commercial Ctr.",
  "1225": "Urdaneta Village",
  "1226": "Ayala-Paseo de Roxas",
  "1227": "Salcedo Village",
  "1228": "Greenbelt",
  "1229": "Legaspi Village",
  "1230": "Pio del Pilar",
  "1231": "Pasong Tamo & Ecology Vill",
  "1232": "Magallanes Village",
  "1233": "Bangkal",
  "1234": "San Isidro",
  "1235": "Palanan",
  "1300": [
    "Mall of Asia Complex (MOA)",
    "Pasay City CPO - Malibay"
  ],
  "1301": "Domestic Airport P.O.",
  "1302": "San Rafael",
  "1303": "San Roque",
  "1304": "Sta. Clara",
  "1305": "San Jose",
  "1306": "San Isidro",
  "1307": "PICC Reclamation Area",
  "1308": "Manila Bay Reclamation",
  "1309": "Villamor Airbase",
  "1400": "Kaloocan City CPO",
  "1401": "Baesa",
  "1402": "Sta. Quiteria",
  "1403": "Grace Park East",
  "1404": "San Jose",
  "1405": "1st to 7th Ave. West",
  "1406": "Grace Park West",
  "1407": "University Hills",
  "1408": "Sangandaan",
  "1409": [
    "Kanluran Village",
    "Kaunlaran Village"
  ],
  "1410": "Maypajo",
  "1411": "Fish Market",
  "1412": "Isla de Cocomo",
  "1413": "Kapitbahayan East",
  "1420": "Kaybiga/Deparo",
  "1421": "Bagumbong/Pag-asa",
  "1422": "Novaliches North",
  "1423": "Lilles Ville Subd.",
  "1424": "Capitol Parkland Subd.",
  "1425": "Amparo Subdivision",
  "1426": "Bankers Village",
  "1427": [
    "Tala Leprosarium",
    "Victory Heights"
  ],
  "1428": "Bagong Silang",
  "1440": "Valenzuela CPO, Malinta",
  "1441": "Karuhatan",
  "1442": "Fortune Village, Paseo de Blas, Gen. T de Leon",
  "1443": "Dalandan West, Canumay",
  "1444": "Arkong Bato, Rincon, Pasolo, Malanday, Mabolo, Polo",
  "1445": "Balangkas, Caloong",
  "1446": "Lingunan",
  "1447": "East Canumay, Lawang Bato Punturin",
  "1448": "Mapulang Lupa",
  "1470": "Malabon",
  "1471": "Flores",
  "1472": "Longos",
  "1473": "Tonsuya",
  "1474": "Acacia",
  "1475": "Potrero",
  "1476": "Araneta Subdivision",
  "1477": "Maysilo",
  "1478": "Santolan",
  "1479": "Muzon",
  "1480": "Dampalit",
  "1485": "Navotas",
  "1489": "Tangos",
  "1490": "Tanza",
  "1496": "Valenzuela P.O. Boxes",
  "1500": "San Juan CPO",
  "1502": "Greenhills PO",
  "1503": "Greenhills North",
  "1504": "Eisenhower-Crame",
  "1550": "Mandaluyong CPO",
  "1551": "Vergara",
  "1552": "Shaw Boulevard",
  "1553": "National Center for Mental Health (Mental Hospital)",
  "1554": "East Edsa",
  "1555": "Wack Wack Golf Club",
  "1556": "Greenhills South",
  "1600": "Pasig CPO",
  "1601": "San Joaquin",
  "1602": "Pinagbuhatan",
  "1603": "Kapitolio",
  "1604": "Ugong",
  "1605": "Ortigas PO",
  "1606": "Caniogan",
  "1607": "Maybunga",
  "1608": "Sta. Lucia",
  "1609": "Rosario",
  "1610": "Santolan",
  "1611": "Manggahan",
  "1612": "Green Park",
  "1620": "Aguho",
  "1621": "Sta. Ana",
  "1630": "Western Bicutan",
  "1631": "Bicutan",
  "1632": "Lower Bicutan",
  "1633": "Upper Bicutan",
  "1634": "Nichols-Mckinley",
  "1636": "Bay Breeze Village",
  "1637": "Tukukan",
  "1638": "Ligid",
  "1700": "Parañaque CPO",
  "1701": "Tambo",
  "1702": "Baclaran",
  "1703": "Marina Subd. (Reclamation)",
  "1704": "Santo Niño",
  "1705": "NAIA (Airport)",
  "1706": "Pulo",
  "1707": "San Antonio Valley 11 & 12",
  "1708": "Multinational Subd.",
  "1709": [
    "Mervile Park Subd.",
    "Moonwalk Subdivision",
    "South Admiral Village"
  ],
  "1710": "Executive Heights Subd.",
  "1711": "Better Living Subd.",
  "1712": "Miramar Subd.",
  "1713": "United Paranaque Subd.",
  "1714": [
    "Aeropark Subdivision",
    "Ireneville 2"
  ],
  "1715": "San Antonio Valley 1",
  "1716": "Maywood 2",
  "1717": "Manila Memorial Park",
  "1718": "BF Homes 2",
  "1719": [
    "Ireneville 1 & 3",
    "Maywood 1"
  ],
  "1720": "BF Homes 1",
  "1740": "Las Pinas CPO",
  "1741": "Remarville Subd.",
  "1742": [
    "Zapote",
    "Pulang Lupa"
  ],
  "1743": "Cut-cut",
  "1744": "Manuyo",
  "1745": "Gatchalian Subd.",
  "1746": "Verdant Acres Subd.",
  "1747": "Talon Moonwalk",
  "1748": "Manila Doctor's Village",
  "1749": "Angela Village",
  "1750": "Almanza",
  "1751": "T. S. Cruz Subd.",
  "1752": "Soldiers Hills Subd.",
  "1770": "Muntinlupa CPO",
  "1771": "Bule/Cupang",
  "1772": "Bayanan/Putatan",
  "1773": "Tunasan",
  "1774": "Susana Heights",
  "1775": "Pearl Heights",
  "1776": "Poblacion",
  "1777": "Pleasant Village",
  "1780": "Ayala Alabang Subd.",
  "1781": "Filinvest Corporate City",
  "1799": "Ayala Alabang P.O. Boxes",
  "1800": "Marikina CPO",
  "1801": "San Roque-Calumpang",
  "1802": "Industrial Valley",
  "1803": [
    "Barangka",
    "Tañong"
  ],
  "1804": "J de la Pena",
  "1805": "Malanday",
  "1806": "North/West of Marikina River",
  "1807": "Conception 1",
  "1808": "Nangka",
  "1809": "Parang",
  "1810": "Marikina Heights",
  "1811": "Conception 2",
  "1820": [
    "Bagong Nayon",
    "Cogeo",
    "Cupang",
    "Langhaya",
    "Mambagat",
    "Mayamot"
  ],
  "1850": "San Mateo",
  "1860": "Montalban (Rodriguez)",
  "1870": "Antipolo",
  "1880": "Teresa",
  "1900": "Cainta",
  "1910": "Pililia",
  "1920": "Taytay",
  "1930": "Angono",
  "1940": "Binangonan",
  "1950": "Cardona",
  "1960": "Morong",
  "1970": "Baras",
  "1980": "Tanay",
  "1990": "Jala-Jala",
  "2000": "San Fernando",
  "2001": "Bacolor",
  "2002": "Santa Rita",
  "2003": "Guagua",
  "2004": "Sasmuan (old: Sexmoan)",
  "2005": "Lubao",
  "2006": "Floridablanca",
  "2007": "Basa Air Base",
  "2008": "Porac",
  "2009": "Angeles City",
  "2010": "Mabalacat",
  "2011": "Magalang",
  "2012": "Arayat",
  "2013": "Candaba",
  "2014": "San Luis",
  "2015": "San Simon",
  "2016": "Apalit",
  "2017": "Masantol",
  "2018": "Macabebe",
  "2019": "Minalin",
  "2020": "Santo Tomas",
  "2021": "Mexico",
  "2022": "Santa Ana",
  "2100": "Balanga",
  "2101": "Pilar",
  "2102": "Orion",
  "2103": "Limay",
  "2104": "Lamao",
  "2105": "Mariveles",
  "2106": "Bataan Export Processing Zone (BEPZ) Mariveles",
  "2107": "Bagac",
  "2108": "Morong",
  "2109": "Refugee Processing Center (Morong)",
  "2110": "Dinalupihan",
  "2111": "Hermosa",
  "2112": "Orani",
  "2113": "Samal",
  "2114": "Bucay",
  "2200": "Olongapo City",
  "2201": "Iba",
  "2202": "Botolan",
  "2203": "Cabangan",
  "2204": "San Felipe",
  "2205": "San Narciso",
  "2206": "San Antonio",
  "2207": "San Marcelino",
  "2208": "Castillejos",
  "2209": "Subic",
  "2210": "Palauig",
  "2211": "Masinloc",
  "2212": "Candelaria",
  "2213": "Sta. Cruz",
  "2300": "Tarlac",
  "2301": "San Miguel",
  "2302": "Gerona",
  "2303": "Sta. Ignacia",
  "2304": "Mayantoc",
  "2305": "San Clemente",
  "2306": "Camiling",
  "2307": "Paniqui",
  "2308": "Mancada",
  "2309": "San Manuel",
  "2310": "Anao",
  "2311": "Ramos",
  "2312": "Pura",
  "2313": "Victoria",
  "2314": "La Paz",
  "2315": "Capas",
  "2316": "Conception",
  "2317": "Bamban",
  "2400": "Dagupan City",
  "2401": "Lingayen",
  "2402": "Labrador",
  "2403": "Sual",
  "2404": "Alaminos",
  "2405": "Anda",
  "2406": "Bolinao",
  "2407": "Bani",
  "2408": "Agno",
  "2409": "Mabini",
  "2410": "Burgos",
  "2411": "Dasol",
  "2412": "Infanta",
  "2413": "Mangatarem",
  "2414": "Urbiztondo",
  "2415": "Aguilar",
  "2416": "Bugallon",
  "2417": "Binmaley",
  "2418": "Calasiao",
  "2419": "Santa Barbara",
  "2420": "San Carlos City",
  "2421": "Malasiqui",
  "2422": "Basista",
  "2423": "Bayambang",
  "2424": "Bautista",
  "2425": "Alcala",
  "2426": "Santo Tomas",
  "2427": "Villasis",
  "2428": "Urdaneta",
  "2429": "Mapandan",
  "2430": "Manaoag",
  "2431": "San Jacinto",
  "2432": "Mangaldan",
  "2433": "San Fabian",
  "2434": "Sison",
  "2435": "Pozorrubio",
  "2436": "Binalonan",
  "2437": "Laoac",
  "2438": "San Manuel",
  "2439": "Asingan",
  "2440": "Santa Maria",
  "2441": "Rosales",
  "2442": "Balungao",
  "2443": "Umingan",
  "2444": "San Quintin",
  "2445": "Tayug",
  "2446": "Natividad",
  "2447": "San Nicolas",
  "2500": "San Fernando",
  "2501": "Bauang",
  "2502": "Caba",
  "2503": "Aringay",
  "2504": "Agoo",
  "2505": "Santo Tomas",
  "2506": "Rosario",
  "2507": "Damortis",
  "2508": "Pugo",
  "2509": "Tubao",
  "2510": "Burgos",
  "2511": "Naguillan",
  "2512": "Bagulin",
  "2513": "San Gabriel",
  "2514": "San Juan",
  "2515": "Bacnotan",
  "2516": "Santol",
  "2517": "Balaoan",
  "2518": "Luna",
  "2519": "Bangar",
  "2520": "Sudepen",
  "2600": "Baguio City",
  "2601": "La Trinidad",
  "2602": "Philippine Military Academy (PMA)",
  "2603": "Tuba",
  "2604": "Itogon",
  "2605": "Bokod",
  "2606": "Kabayan",
  "2607": "Bugias",
  "2608": "Mankayan",
  "2609": "Lepanto",
  "2610": "Bakun",
  "2611": "Kibungan",
  "2612": "Atok",
  "2613": "Kapangan",
  "2614": "Sablan",
  "2615": "Tublay",
  "2616": "Bontoc",
  "2617": "Sadanga",
  "2618": "Besao",
  "2619": "Sagada",
  "2620": "Tadian",
  "2621": "Bauko",
  "2622": "Sabangan",
  "2623": "Barlig",
  "2624": "Natonin",
  "2625": "Paracelis",
  "2700": "Vigan",
  "2701": "Santa Catalina",
  "2702": "Caoayan",
  "2703": "Santa",
  "2704": "Narvacan",
  "2705": "Santa Maria",
  "2706": "San Esteban",
  "2707": "Santiago",
  "2708": "Binayoyo",
  "2709": "Galimuyod",
  "2710": "Candon",
  "2711": "Salsedo",
  "2712": "Santa Lucia",
  "2713": "Santa Cruz",
  "2714": "Tagudin",
  "2715": "Suyo",
  "2716": "Alilem",
  "2717": "Sugpon",
  "2718": "Cervantes",
  "2719": "Sicay",
  "2720": "Gregorio del Pilar",
  "2721": "Quirino",
  "2722": "San Emilio",
  "2723": "Lidilda",
  "2724": "Burgos",
  "2725": "Nagbukel",
  "2726": "San Vicente",
  "2727": "Bantay",
  "2728": "San Ildefonso",
  "2729": "Santo Domingo",
  "2730": "Magsingal",
  "2731": "San Juan",
  "2732": "Cabugao",
  "2733": "Sinait",
  "2800": "Bangued",
  "2801": "Dolores",
  "2802": "Langagilang",
  "2803": "Tayum",
  "2804": "Peñarubia",
  "2805": "Bucay",
  "2806": "Pidigan",
  "2807": "Langiden",
  "2808": "San Quintin",
  "2809": "San Isidro",
  "2810": "Manabo",
  "2811": "Villaviciosa",
  "2812": "Pilar",
  "2813": "Luba",
  "2814": "Tubo",
  "2815": "Boliney",
  "2816": "Daguioman",
  "2817": "Bucloc",
  "2818": "Sal-Lapadan",
  "2819": "Licuan (Baay)",
  "2820": "Malibcong",
  "2821": "Lacub",
  "2822": "Tineg",
  "2823": "San Juan",
  "2824": "Lagayan",
  "2825": "Danglas",
  "2826": "La Paz",
  "2900": "Laoag City",
  "2901": "San Nicolas",
  "2902": "Paoay",
  "2903": "Currimao",
  "2904": "Badoc",
  "2905": "Pinili",
  "2906": "Batac",
  "2907": "Marcos",
  "2908": "Espiritu",
  "2909": "Nueva Era",
  "2910": "Solsona",
  "2911": "Carasi",
  "2912": "Piddig",
  "2913": "Dingras",
  "2914": "Sarrat",
  "2915": "Vintar",
  "2916": "Bacarra",
  "2917": "Pasuquin",
  "2918": "Burgos",
  "2919": "Pagudpud",
  "2920": "Bangui",
  "2921": "Dumalneg",
  "2922": "Adams",
  "3000": "Malolos",
  "3001": "Paombong",
  "3002": "Hagonoy",
  "3003": "Calumpit",
  "3004": "Plaridel",
  "3005": "Pulilan",
  "3006": "Baliuag",
  "3007": "Bustos",
  "3008": "San Rafael",
  "3009": "Dona Remedios Trinidad",
  "3010": "San Ildefonso",
  "3011": "San Miguel",
  "3012": "Angat",
  "3013": "Norzagaray",
  "3014": "Pandi",
  "3015": "Guiguinto",
  "3016": "Balagtas",
  "3017": "Bulacan",
  "3018": "Bocaue",
  "3019": "Marilao",
  "3020": "Maycauayan",
  "3021": "Obando",
  "3022": "Santa Maria",
  "3023": "San Jose del Monte",
  "3024": "Sapang Palay",
  "3100": "Cabanatuan City",
  "3101": "Santa Rosa",
  "3102": "San Leonardo",
  "3103": "Penaranda",
  "3104": "Gen. Tinio",
  "3105": "Gapan",
  "3106": "San Isidro",
  "3107": "Cabiao",
  "3108": "San Antonio",
  "3109": "Jaen",
  "3110": "Zaragosa",
  "3111": "Aliaga",
  "3112": "Lucab",
  "3113": "Quezon",
  "3114": "Talavera",
  "3115": "Guimba",
  "3116": "Nampicuan",
  "3117": "Cuyapao",
  "3118": "Talugtog",
  "3119": "Munoz",
  "3120": "Central Luzon State University (CLSU)",
  "3121": "San Jose City",
  "3122": "Lupao",
  "3123": "Carranglan",
  "3124": "Pantabangan",
  "3125": "Gen. M. Natividad",
  "3126": "Llanera",
  "3127": "Rizal",
  "3128": "Bongabon",
  "3129": "Laur",
  "3130": "Fort Magsaysay",
  "3131": "Gabaldon",
  "3132": "Palayan City",
  "3133": "Santo Domingo",
  "3200": "Baler",
  "3201": "San Luis",
  "3202": "Maria Aurora",
  "3203": "Dipaculao",
  "3204": "Casiguran",
  "3205": "Dilasag",
  "3206": "Dinalungan",
  "3207": "Dingalan",
  "3300": "Ilagan",
  "3301": "Gamu",
  "3302": "Naguillan",
  "3303": "Reina Mercedes",
  "3304": "Luna",
  "3305": "Cauayan",
  "3306": "Alicia",
  "3307": "Angadanan",
  "3308": "San Guillermo",
  "3309": "Echague",
  "3310": "San Isidro",
  "3311": "Santiago",
  "3312": "Cordon",
  "3313": "Jones",
  "3314": "San Agustin",
  "3315": "Cabatuan",
  "3316": "Aurora",
  "3317": "San Miguel (Callang)",
  "3318": "San Mateo",
  "3319": "Ramon",
  "3320": "Roxas",
  "3321": "Quirino",
  "3322": "Burgos",
  "3323": "Mallig",
  "3324": "Quezon",
  "3325": "Tumauini",
  "3326": "Delfin Albano",
  "3327": "Santo Tomas",
  "3328": "Cabagan",
  "3329": "San Pablo",
  "3330": "Santa Maria",
  "3331": "Benito Soliven",
  "3332": "San Mariano",
  "3333": "Maconacon",
  "3334": "Palanan",
  "3335": "Divilacan",
  "3336": "Dinapigui",
  "3400": "Cabarruguis",
  "3401": "Diffun",
  "3402": "Saguday",
  "3403": "Aglipay",
  "3404": "Maddela",
  "3405": "Nagtipunan (Abbag)",
  "3500": "Tuguegarao",
  "3501": "Enrile",
  "3502": "Penablanca",
  "3503": "Solana",
  "3504": "Iguig",
  "3505": "Amulung",
  "3506": [
    "Alcala",
    "Baggao"
  ],
  "3508": "Gattaran",
  "3509": "Lal-lo",
  "3510": "Camalaniugan",
  "3511": [
    "Buguey",
    "Gonzaga"
  ],
  "3512": "Santa Teresita",
  "3514": "Santa Ana",
  "3515": "Aparri",
  "3516": "Ballesteros",
  "3517": "Abulog",
  "3518": "Sanchez Mira",
  "3519": "Claveria",
  "3520": "Calayan",
  "3521": "Santa Praxedes",
  "3522": "Pamplona",
  "3523": "Allacapan",
  "3524": "Lasam",
  "3525": "Santo Nino",
  "3526": "Rizal",
  "3527": "Piat",
  "3528": "Tuao",
  "3600": "Lagawe",
  "3601": "Banaue",
  "3602": "Mayaoyao / Mayoyao",
  "3603": "Hungduan",
  "3604": "Kiangan",
  "3605": "Lamut",
  "3606": "Aguinaldo",
  "3607": "Hingyon",
  "3608": "Potia",
  "3609": "Tinoc",
  "3610": "Asipulo",
  "3700": "Bayombong",
  "3701": "Ambaguio",
  "3702": "Bambang",
  "3703": "Kasibu",
  "3704": "Aritao",
  "3705": "Sta. Fe (Imugan)",
  "3706": "Dupax del Norte",
  "3707": "Dupax del Sur",
  "3708": "Kayapa",
  "3709": "Solano",
  "3710": "Villa Verde (Ibung)",
  "3711": "Bagabag",
  "3712": "Diadi",
  "3713": "Quezon",
  "3714": "Alfonso Castañeda",
  "3800": "Tabuk",
  "3801": "Balbalan",
  "3802": "Lubuagan",
  "3803": "Pasil",
  "3804": "Tinglayan",
  "3805": "Tanudan",
  "3806": "Pinukpuk",
  "3807": [
    "Conner",
    "Flora"
  ],
  "3808": "Liwan (Rizal)",
  "3809": "Kabugao",
  "3811": "Santa Marcela",
  "3812": "Pudtol",
  "3813": "Luna",
  "3814": "Calanasan",
  "3900": "Basco",
  "3901": "Mahatao",
  "3902": "Ivana",
  "3903": "Uyugan",
  "3904": "Sabtang",
  "3905": "Itbayat",
  "4000": "San Pablo City",
  "4001": "Alaminos",
  "4002": "Nagcarlan",
  "4003": "Rizal",
  "4004": "Liliw",
  "4005": "Majayjay",
  "4006": "Botocan",
  "4007": "Magdalena",
  "4008": "Pagsanjan",
  "4009": "Santa Cruz",
  "4010": "Pila",
  "4011": "Victoria",
  "4012": "Calauan",
  "4013": "Cavinti",
  "4014": "Lumban",
  "4015": "Kalayaan",
  "4016": "Paete",
  "4017": "Pakil",
  "4018": "Pangil",
  "4019": "Siniloan",
  "4020": "Mabitac",
  "4021": "Famy",
  "4022": "Santa Maria",
  "4023": "San Pedro",
  "4024": "Binan",
  "4025": "Cabuyao",
  "4026": "Santa Rosa",
  "4027": "Calamba",
  "4028": "Canlubang",
  "4029": "Camp Vicente Lim",
  "4030": "Los Banos",
  "4031": "College Los Banos",
  "4032": "Luisiana",
  "4033": "Bay",
  "4100": "Cavite City",
  "4101": "Cavite Naval Base",
  "4102": "Bacoor",
  "4103": "Imus",
  "4104": "Kawit",
  "4105": "Noveleta",
  "4106": "Rosario",
  "4107": "Gen. Trias",
  "4108": "Tanza",
  "4109": "Trece Martirez City",
  "4110": "Naic",
  "4111": "Ternate",
  "4112": "Maragondon",
  "4113": "Magallanes",
  "4114": "Dasmarinias",
  "4115": "Dasmarinias Resettlement Area",
  "4116": "Carmona",
  "4117": "Gen. Mariano Alvarez",
  "4118": "Silang",
  "4119": "Amadeo",
  "4120": "Tagaytay City",
  "4121": "Mendez",
  "4122": "Indang",
  "4123": "Alfonso",
  "4124": "Gen. Aguinaldo (Bailen)",
  "4125": "Corregidor",
  "4200": "Batangas City",
  "4201": "Bauan",
  "4202": "Mabini",
  "4203": "Tingloy",
  "4204": "San Pascual",
  "4205": "Alitagtag",
  "4206": "Santa Teresita",
  "4207": "San Nicolas",
  "4208": "Taal",
  "4209": "Lemery",
  "4210": "San Luis",
  "4211": "Agoncillo",
  "4212": "Calaca",
  "4213": "Balayan",
  "4214": "Uy",
  "4215": "Calatagan",
  "4216": "Lian",
  "4217": "Lipa City",
  "4218": "Fernando Air Base",
  "4219": "Balite",
  "4220": "Talisay",
  "4221": "Laurel",
  "4222": "Cuenca",
  "4223": "Mataas na Kahoy",
  "4224": "Padre Garcia",
  "4225": "Rosario",
  "4226": "San Juan",
  "4227": "San Jose",
  "4228": "Taysan",
  "4229": "Lobo",
  "4230": "Ibaan",
  "4231": "Nasugbu",
  "4232": "Tanauan",
  "4233": "Malvar",
  "4234": "Santo Tomas",
  "4300": "Quezon Capitol",
  "4301": "Lucena City",
  "4302": "Pagbilao",
  "4303": "Padre Burgos",
  "4304": "Agdangan",
  "4305": "Unisan",
  "4306": [
    "Gumaca",
    "Plaridel"
  ],
  "4308": "Pitogo",
  "4309": "Macalelon",
  "4310": "Gen. Luna",
  "4311": "Catanuan",
  "4312": "Mulanay",
  "4313": "San Narciso",
  "4314": "San Andres",
  "4315": "San Francisco",
  "4316": "Lopez",
  "4317": "Hondagua",
  "4318": "Calauag",
  "4319": "Guinayangan",
  "4320": "Buenavista",
  "4321": "Tagkawayan",
  "4322": "Sariaya",
  "4323": "Candelaria",
  "4324": "San Antonio",
  "4325": "Tiaong",
  "4326": "Dolores",
  "4327": "Tayabas",
  "4328": "Lucban",
  "4329": "Sampaloc",
  "4330": "Mauban",
  "4331": "Atimonan",
  "4332": "Quezon",
  "4333": "Alabat",
  "4334": "Perez",
  "4335": "Real",
  "4336": "Infanta",
  "4337": "Panukulan",
  "4338": "Gen. Nakar",
  "4339": "Polilio",
  "4340": "Burdeos",
  "4341": "Patnonangan",
  "4342": "Jomalig",
  "4400": "Naga City",
  "4401": "Camaligan",
  "4402": "Canaman",
  "4403": "Magarao",
  "4404": "Bombon",
  "4405": "Calabanga",
  "4406": "Cabusao",
  "4407": "Libmanan",
  "4408": "Sipocot",
  "4409": "Lupi",
  "4410": "Ragay",
  "4411": "Del Gallego",
  "4412": "Gainza",
  "4413": "Milaor",
  "4414": "Minalabac",
  "4415": "San Fernando",
  "4416": "Pamplona",
  "4417": "Pasacao",
  "4418": "Pili",
  "4419": "Ocampo",
  "4420": "Tigaon",
  "4421": "Sagnay",
  "4422": "Goa",
  "4423": "San Jose",
  "4424": "Presentacion",
  "4425": "Lagunoy",
  "4426": "Tinambac",
  "4427": "Siruma",
  "4428": "Garchitorena",
  "4429": "Caramoan",
  "4430": "Bula",
  "4431": "Iriga City",
  "4432": "Baao",
  "4433": "Buhi",
  "4434": "Nabua",
  "4435": "Bato",
  "4436": "Balatan",
  "4500": "Legaspi City",
  "4501": "Daraga (Locsin)",
  "4502": "Camalig",
  "4503": "Guinobatan",
  "4504": [
    "Ligao",
    "Oas"
  ],
  "4506": "Polangui",
  "4507": "Libon",
  "4508": "Sto. Domingo",
  "4509": "Bacacay",
  "4510": "Malilipot",
  "4511": "Tabaco",
  "4512": "Malinao",
  "4513": "Tiwi",
  "4514": "Manito",
  "4515": "Jovellar",
  "4516": "Pio Duran (Malacbalac)",
  "4517": "Rapu-rapu",
  "4600": "Daet",
  "4601": "Mercedez",
  "4602": "Talisay",
  "4603": "Vinzons",
  "4604": "Labo",
  "4605": "Paracale",
  "4606": [
    "Capalonga",
    "Jose Panganiban"
  ],
  "4608": "Basud",
  "4609": "San Vicente",
  "4610": "Imelda",
  "4611": "Santa Elena",
  "4612": "Tulay na Lupa",
  "4700": "Sorsogon",
  "4701": "Bacon",
  "4702": "Casiguran",
  "4703": "Juban",
  "4704": "Bulusan",
  "4705": "Magallanes",
  "4706": "Bulan",
  "4707": "Irosin",
  "4708": "Matnog",
  "4709": "Sta. Magdalena",
  "4710": "Gubat",
  "4711": "Prieto Diaz",
  "4712": "Barcelona",
  "4713": "Castilla",
  "4714": "Pilar",
  "4715": "Donsol",
  "4800": "Virac",
  "4801": "Bato",
  "4802": "San Miguel",
  "4803": "Baras",
  "4804": "Gigmoto",
  "4805": "Viga",
  "4806": "Panganiban",
  "4807": "Bagamanoc",
  "4808": "Caramoran",
  "4809": "Pandan",
  "4810": "San Andres",
  "4900": "Boac",
  "4901": "Mogpog",
  "4902": "Santa Cruz",
  "4903": "Torrijos",
  "4904": "Buenavista",
  "4905": "Gasan",
  "5000": "Iloilo City",
  "5001": "Pavia",
  "5002": "Santa Barbara",
  "5003": "Leganes",
  "5004": "Zarraga",
  "5005": "New Lucena",
  "5006": "Dumangas",
  "5007": "Barotac Nuevo",
  "5008": "Pototan",
  "5009": "Anilao",
  "5010": "Banate",
  "5011": "Barotac Viejo",
  "5012": "Ajuy",
  "5013": "Conception",
  "5014": "Sara",
  "5015": "San Dionisio",
  "5016": "Batad",
  "5017": "Estancia",
  "5018": "Balasan",
  "5019": "Carles",
  "5020": "Oton",
  "5021": "Tigbauan",
  "5022": "Guimbal",
  "5023": "Miagao",
  "5024": "San Joaquin",
  "5025": "San Miguel",
  "5026": "Leon",
  "5027": "Tubungan",
  "5028": "Alimodian",
  "5029": "Igbaras",
  "5030": "Maasin",
  "5031": "Cabatuan",
  "5032": "Mina",
  "5033": "Badiangan",
  "5034": "Janiuay",
  "5035": "Dingle",
  "5036": "San Enrique",
  "5037": "Passi",
  "5038": "Dueñas",
  "5039": "San Rafael",
  "5040": "Calinog",
  "5041": "Bingawan",
  "5042": "Lambunao",
  "5043": "Lemery",
  "5044": "Buenavista",
  "5045": "Jordan",
  "5046": "Nueva Valencia",
  "5100": "San Jose",
  "5101": "Magsaysay",
  "5102": "Calintaan",
  "5103": "Rizal",
  "5104": "Sablayan",
  "5105": "Santa Cruz",
  "5106": "Mamburao",
  "5107": "Paluan",
  "5108": "Abra de Ilog",
  "5109": "Lubang",
  "5110": "Tilik",
  "5111": "Looc",
  "5200": "Calapan",
  "5201": "Baco",
  "5202": "San Teodoro",
  "5203": "Puerto Galera",
  "5205": "Victoria",
  "5206": "Pola",
  "5207": "Socorro",
  "5208": "Mansalay",
  "5209": "Gloria",
  "5210": "Bansud",
  "5211": "Bongabon",
  "5212": "Roxas",
  "5214": "Bulalacao",
  "5300": "Puerto Princesa City",
  "5301": "Iwahig Penal Colony",
  "5302": "Aborlan",
  "5303": "Narra (Panacan)",
  "5304": "Quezon",
  "5305": "Brooke's Point",
  "5306": "Bataraza",
  "5307": "Balabac",
  "5308": "Roxas",
  "5309": "San Vicente",
  "5310": "Dumaran",
  "5311": "Araceli",
  "5312": "Taytay",
  "5313": "El Nido (Baquit)",
  "5314": "Linapacan",
  "5315": "Culion",
  "5316": "Coron",
  "5317": "Busuanga",
  "5318": "Cuyo",
  "5319": "Magsaysay",
  "5320": "Agutaya",
  "5321": "Cagayancillo",
  "5322": "Kalayaan",
  "5400": "Masbate",
  "5401": "Mobo",
  "5402": "Uson",
  "5403": "Dimasalang",
  "5404": "Palanas",
  "5405": [
    "Cataingan",
    "Cawayan"
  ],
  "5406": "Pio V. Cruz",
  "5407": "Esperanza",
  "5408": "Placer",
  "5410": "Milagros",
  "5411": "Mandaon",
  "5412": "Balud",
  "5413": "Baleno",
  "5414": "Aroroy",
  "5415": "Batuan",
  "5416": "San Fernando",
  "5417": "San Jacinto",
  "5418": "Montreal",
  "5419": "Claveria",
  "5420": "San Pascual",
  "5421": "Buenavista",
  "5500": "Romblon",
  "5501": "San Agustin",
  "5502": "Imelda",
  "5503": "Calatrava",
  "5504": "San Andres",
  "5505": "Odiongan",
  "5506": "Ferrol",
  "5507": "Looc",
  "5508": "Santa Fe",
  "5509": "Alcantara",
  "5510": "San Jose",
  "5511": "Magdiwang",
  "5512": "Cajidiocan",
  "5513": "San Fernando",
  "5514": "Corcuera",
  "5515": "Banton (Jones)",
  "5516": "Conception",
  "5600": "Kalibo",
  "5601": "Banga",
  "5602": "Libacao",
  "5603": "Madalag",
  "5604": "Numancia",
  "5605": "Lezo",
  "5606": "Malinao",
  "5607": "Nabas",
  "5608": "Malay",
  "5609": "Buruanga",
  "5610": "New Washington",
  "5611": "Makato",
  "5612": "Tangalan",
  "5613": "Ibajay",
  "5614": "Balite",
  "5615": "Batan",
  "5616": "Altavas",
  "5700": "San Jose",
  "5701": "Belison",
  "5702": "Patnongan",
  "5703": "Valderama",
  "5704": "Bugasong",
  "5705": "Lawa-an",
  "5706": "Barbasa",
  "5707": "Tibiao",
  "5708": "Culasi",
  "5709": "Sebaste",
  "5710": "Libertad",
  "5711": "Caluya",
  "5712": "Pandan",
  "5713": "Sibalom",
  "5714": "San Remedio",
  "5715": "Hamtic",
  "5716": "Tobias Fornier (Dao)",
  "5717": "Anini-y",
  "5800": "Roxas City",
  "5801": "Panay",
  "5802": "Puntevedra",
  "5803": "Pres. Roxas",
  "5804": "Pilar",
  "5805": "Ivisan",
  "5807": "Mambusao",
  "5808": "Jamindan",
  "5809": "Ma-ayon",
  "5810": "Dao",
  "5811": "Cuartero",
  "5812": "Dumarao",
  "5813": "Dumalag",
  "5814": "Tapaz",
  "5815": "Panitan",
  "5816": "Sapian",
  "6000": "Cebu City",
  "6001": "Consolacion",
  "6002": "Liloan",
  "6003": "Compostela",
  "6004": "Danao",
  "6005": "Carmen",
  "6006": "Catmon",
  "6007": "Sogod",
  "6008": "Borbon",
  "6009": "Tabogon",
  "6010": "Bogo",
  "6011": "San Remegio",
  "6012": "Medellin",
  "6013": "Daang-Bantayan",
  "6014": "Mandaue City",
  "6015": "Lapu-Lapu City",
  "6016": "Mactan Airport",
  "6017": "Cordova",
  "6018": "San Fernando",
  "6019": "Carcar",
  "6020": "Sibonga",
  "6021": "Argao",
  "6022": "Dalaguete",
  "6023": "Alcoy",
  "6024": "Boljoon",
  "6025": "Oslob",
  "6026": [
    "Ginatilan",
    "Santander"
  ],
  "6027": "Samboan",
  "6029": "Malabuyoc",
  "6030": "Alegria",
  "6031": "Badian",
  "6032": "Moalboal",
  "6033": "Alcantara",
  "6034": "Ronda",
  "6035": "Dumanjug",
  "6036": "Barile",
  "6037": "Naga",
  "6038": "Toledo City",
  "6039": "Pinamungahan",
  "6040": "Aloguinsan",
  "6041": "Balamban",
  "6042": [
    "Asturias",
    "Bantayan"
  ],
  "6043": "Tuburan",
  "6044": "Tabuelan",
  "6045": "Talisay",
  "6046": "Minglanilla",
  "6047": "Santa Fe",
  "6048": "Pilar",
  "6049": "Poro",
  "6050": "San Francisco",
  "6051": "Todela",
  "6053": "Madridejos",
  "6100": [
    "Bacolod City",
    "Kabangkalan"
  ],
  "6101": "Bago City",
  "6102": "Pulupandan",
  "6103": "Villadolid",
  "6104": "San Enrique",
  "6105": "Pontevedra",
  "6106": "Hinigaran",
  "6107": "Binalbagan",
  "6108": "Himamaylan",
  "6109": "Ilog",
  "6110": "Candoni",
  "6112": "Kauayan",
  "6113": "Sipalay",
  "6114": "Hinoba-ari",
  "6115": "Talisay",
  "6116": "Silay City",
  "6117": "Silay Hawaiian Central",
  "6118": "Enrique Magalona",
  "6119": "Victorias",
  "6120": "Manapla",
  "6121": "Cadiz City",
  "6122": "Sagay",
  "6123": "Paraiso (Fabrica)",
  "6124": "Escalante",
  "6125": "Toboso",
  "6126": "Calatrava",
  "6127": "San Carlos City",
  "6128": "Isabela",
  "6129": "Murcia",
  "6130": "La Carlota City",
  "6131": "La Castillana",
  "6132": "Moises Padilla",
  "6200": "Dumaguete City",
  "6201": "Sibulan",
  "6202": "San Jose",
  "6203": "Amian",
  "6204": "Tanjay",
  "6205": "Pamplona",
  "6206": "Bais City",
  "6208": [
    "Mabinay",
    "Manjuyod"
  ],
  "6209": "Bindoy",
  "6210": "Ayungon",
  "6211": "Tayasan",
  "6212": "Jimalalud",
  "6213": "La Libertad",
  "6214": "Guihulngan",
  "6215": "Valencia",
  "6216": "Bacung",
  "6217": "Dauin",
  "6218": "Zamboanguita",
  "6219": "Siaton",
  "6220": "Sta. Catalina",
  "6221": "Bayawan",
  "6222": "Basay",
  "6223": "Canlaon City",
  "6224": "Valle Hermoso",
  "6225": "Siquijor",
  "6226": "Larena",
  "6227": "San Juan",
  "6228": "Lazi",
  "6229": "Maria",
  "6230": "Enrile Villanueva",
  "6300": "Tagbilaran City",
  "6301": "Baclayon",
  "6302": "Albuquerque",
  "6303": "Loay",
  "6304": "Lila",
  "6305": "Dimiao",
  "6306": "Valencia",
  "6307": "Garcia Hernandez",
  "6308": "Jagna",
  "6309": "Duero",
  "6310": "Guindulman",
  "6311": "Anda",
  "6312": "Candijay",
  "6313": "Mabini",
  "6314": "Alicia",
  "6315": "Ubay",
  "6316": "Loboc",
  "6317": "Bilar",
  "6318": "Batuan",
  "6319": "Carmen",
  "6320": "Sierra Bullones",
  "6321": "Pilar",
  "6322": "Daguhoy",
  "6323": "San Miguel",
  "6324": "Trinidad",
  "6325": "Talibon",
  "6326": "Bien Unido",
  "6327": "Loon",
  "6328": "Calape",
  "6329": "Tubigon",
  "6330": "Clarin",
  "6331": "Sagbayan",
  "6332": "Inabanga",
  "6333": "Buenavista",
  "6334": "Jetafe",
  "6335": "Antiquera",
  "6336": "Maribujok",
  "6337": "Corella",
  "6338": "Sikatuna",
  "6339": "Dauis",
  "6340": "Panglao",
  "6341": "Cortez",
  "6342": "Balilihan",
  "6343": "Catigbi-an",
  "6344": "Danao",
  "6345": "San Isidro",
  "6346": "Carlos P. Garcia (Dao)",
  "6347": "Sevilla",
  "6400": "Catarman",
  "6401": "Bobon",
  "6402": "San Jose",
  "6403": "Lope de Vega",
  "6404": "Lavezares",
  "6405": "Allen",
  "6406": "Victoria",
  "6407": "San Antonio",
  "6408": "Capul",
  "6409": "San Isidro",
  "6410": "Biri",
  "6411": "Laoang",
  "6412": "Mapanas",
  "6413": "Pambujan",
  "6414": "Silvino Lubos",
  "6415": "San Roque",
  "6416": "Rosario",
  "6417": "Mondragon",
  "6418": "Catubig",
  "6419": "San Vicente",
  "6420": "La Navas",
  "6421": "Palapag",
  "6422": "Gamay",
  "6423": "Lapineg",
  "6500": "Tacloban City",
  "6501": "Palo",
  "6502": "Tanauan",
  "6503": "Tolosa",
  "6504": "Tabontabon",
  "6505": "Dulag",
  "6506": "Julita",
  "6507": "Mayorga",
  "6508": "La Paz",
  "6509": "Macarthur",
  "6510": "Abuyog",
  "6511": "Javier",
  "6512": "Mahaplag",
  "6513": "Santa Fe",
  "6514": "Pastrana",
  "6515": "Dagami",
  "6516": "Burauen",
  "6517": "Alangalang",
  "6518": "San Miguel",
  "6519": "Barugo",
  "6520": "Babatngon",
  "6521": "Baybay",
  "6522": "Inopacan",
  "6523": "Hindang",
  "6524": "Hilongos",
  "6525": "Bato",
  "6526": "Matalom",
  "6527": "Jaro",
  "6528": "Tunga",
  "6529": "Carigara",
  "6530": "Capoocan",
  "6531": "Kananga",
  "6532": "Matag-Ob",
  "6533": "Leyte",
  "6534": "Calubian",
  "6535": "San Isidro",
  "6536": "Tabango",
  "6537": "Villaba",
  "6538": "Palumpon",
  "6539": "Isabel",
  "6540": "Merida",
  "6541": "Ormoc City",
  "6542": "Albuera",
  "6543": "Naval",
  "6544": "Almeria",
  "6545": "Kawayan",
  "6546": "Maripipi",
  "6547": "Culaba",
  "6548": "Caibiran",
  "6549": "Biliran",
  "6550": "Cabuccayan",
  "6600": "Maasin",
  "6601": "Macrohon",
  "6602": "Padre Burgos",
  "6603": "Malitbog",
  "6604": "Bomtoc",
  "6605": "Tomas Oppus",
  "6606": "Sogod",
  "6607": "Silago",
  "6608": "Hinunangan",
  "6609": "Hinundayan",
  "6610": "Anahawan",
  "6611": "San Juan (Cabalian)",
  "6612": "Liloan",
  "6613": "San Francisco",
  "6614": "Pintuyan",
  "6615": "Libagon",
  "6616": "St. Bernard",
  "6617": "San Ricardo",
  "6700": "Catbalogan",
  "6701": "Jiabong",
  "6702": "Motiong",
  "6703": "Wright",
  "6704": "Tarangnan",
  "6705": "Pagsanjan",
  "6706": "Gandara",
  "6707": "San Jorge",
  "6708": "Matuguinao",
  "6709": "Sta. Margarita",
  "6710": "Calbayog City",
  "6711": "Sto. Nino",
  "6712": "Tagapulan",
  "6713": "Hinbangan",
  "6714": "San Sebastian",
  "6715": "Calbiga",
  "6716": "Pinabacdao",
  "6717": "Villareal",
  "6718": "Sta. Rita",
  "6719": "Talarora",
  "6720": "Basey",
  "6721": "Marabut",
  "6722": "Daram",
  "6723": "San Jose de Bauan",
  "6724": "Almagro",
  "6725": "Zumarraga",
  "6800": "Borongan",
  "6801": "Balangkayan",
  "6802": "Maydulog",
  "6803": "Llorente",
  "6804": "Hernani",
  "6805": "Gen. McArthur",
  "6806": "Can-Avid",
  "6807": "Salcedo",
  "6808": "Mercedes",
  "6809": "Guiuan",
  "6810": "Quinapundan",
  "6811": "Giporlos",
  "6812": "Balangiga",
  "6813": "Lawa-an",
  "6814": "San Julian",
  "6815": "Sulat",
  "6816": "Taft",
  "6817": "Dolores",
  "6818": "Oras",
  "6819": "Jipapad",
  "6820": "Maslog",
  "6821": "San Policarpio",
  "6822": "Arteche",
  "7000": "Zamboanga City",
  "7001": "Ipil",
  "7002": "Reseller Lim",
  "7003": "Titay",
  "7004": "Naga",
  "7005": "Kabasalan",
  "7006": "Siay",
  "7007": "Imelda",
  "7008": "Payao",
  "7009": "Buug",
  "7010": "Mabuhay",
  "7011": "Bayog",
  "7012": "Talusan",
  "7013": "Kumalarang",
  "7014": "Lakewood",
  "7015": "Dumalinao",
  "7016": "Pagadian City",
  "7017": "Labangan",
  "7018": "Tungawan",
  "7019": "Tukuran",
  "7020": "Aurora",
  "7021": "Midsalip",
  "7022": "Don Mariano Marcos",
  "7023": "Molave",
  "7024": "Ramon Magsaysay",
  "7025": "Tambulig",
  "7026": "Mahayag",
  "7027": "Josefina",
  "7028": "Dumingag",
  "7029": "San Miguel",
  "7030": "Dinas",
  "7031": "San Pablo",
  "7032": "Dimataling",
  "7033": "Pitogo",
  "7034": "Tabina",
  "7035": "Margo Sa Tubig",
  "7036": "Vicencio Sagun",
  "7037": "Lapuyan",
  "7038": "Malangas",
  "7039": "Diplahan",
  "7040": "Alicia",
  "7041": "Olutanga",
  "7042": "Guipos",
  "7043": "Tigbad",
  "7100": "Dipolog City",
  "7101": "Dapitan City",
  "7102": "Roxas",
  "7103": "Sibutad",
  "7104": "Rizal",
  "7105": "Pinan",
  "7106": "Polanco",
  "7107": "Mutia",
  "7108": [
    "Gutalac",
    "Sergio Osmena"
  ],
  "7109": "Katipunan",
  "7110": "Manukan",
  "7111": "Jose Dalman (Ponot)",
  "7112": "Sindangan (Leon B. Postigo)",
  "7113": "Siayan",
  "7114": "Salug",
  "7115": "Liloy",
  "7116": "Tampilisan",
  "7117": "Labason",
  "7119": "La Libertad",
  "7120": "Siocon",
  "7121": "Siraway",
  "7122": "Sibuco",
  "7123": "Baliguian",
  "7124": "Kalawit",
  "7200": "Ozamis City",
  "7201": "Clarin",
  "7202": "Tudela",
  "7203": "Sinacaban",
  "7204": "Jimenez",
  "7205": "Panaon",
  "7206": "Aloran",
  "7207": "Oroquieta City",
  "7208": "Lopez Jaena",
  "7209": "Plaridel",
  "7210": "Calamba",
  "7211": "Baliangao",
  "7212": "Sapang Dalaga",
  "7213": "Concepcion",
  "7214": "Tangub City",
  "7215": "Bonifacio",
  "7300": "Isabela de Basilan",
  "7301": "Lantawan",
  "7302": "Lamitan",
  "7303": "Maluso",
  "7304": "Tipo-tipo",
  "7305": "Sumisip",
  "7306": "Tuburan",
  "7400": "Jolo",
  "7401": "Patikul",
  "7402": "Panamao",
  "7403": "Talipao",
  "7404": "Luuk",
  "7405": "Pata",
  "7406": "Tongkil",
  "7407": "Indanan",
  "7408": "Parang",
  "7409": "Maimbung",
  "7410": "Tapul",
  "7411": "Lugus",
  "7412": "Siasi",
  "7413": "Marungas",
  "7414": "Panguntaran",
  "7415": "Panglima Estino",
  "7416": "Kalingalan Kalauang",
  "7500": "Bongao",
  "7501": "Balimbing",
  "7502": "Tandu Bas",
  "7503": "Sapa-sapa",
  "7504": "South Ubian",
  "7505": "Simunol",
  "7506": "Sitangkai",
  "7507": "Taganak (Turtle Island)",
  "7508": "Cagayan de Sulu",
  "7509": "Languyan",
  "8000": "Davao City",
  "8001": "Santa Cruz",
  "8002": "Digos",
  "8003": "Matanao",
  "8004": "Magsaysay",
  "8005": "Bansalan",
  "8006": "Hagunoy",
  "8007": "Padada",
  "8008": "Kiblawan",
  "8010": "Malalag",
  "8011": "Santa Maria",
  "8012": "Malita",
  "8013": "Don Marcelino",
  "8014": "Jose Abad Santos",
  "8015": "Sarangani",
  "8100": "Tagum",
  "8101": "Carmen",
  "8102": "Asuncion",
  "8103": "San Vicente",
  "8104": "New Corella",
  "8105": "Panabo",
  "8112": "Santo Tomas",
  "8113": "Kapalong",
  "8116": "San Mariano",
  "8118": "Babak",
  "8119": "Samal",
  "8120": "Kaputian",
  "8200": "Mati",
  "8201": "Tarragona",
  "8202": "Manay",
  "8203": "Caraga",
  "8204": "Baganga",
  "8205": "Cateel",
  "8206": "Boston",
  "8207": "Lopon",
  "8208": "Banaybanay",
  "8209": "San Isidro",
  "8210": "Gov. Generoso",
  "8300": "Tandag",
  "8301": "San Miguel",
  "8302": "Tago",
  "8303": "Bayabas",
  "8305": "San Agustin",
  "8306": "Marihatag",
  "8307": "Lianga",
  "8308": "Tagbina",
  "8309": "Barobo",
  "8310": "Hinatuan",
  "8311": [
    "Bislig",
    "Cagwait"
  ],
  "8312": "Lingig",
  "8313": "Cortez",
  "8314": "Lanuza",
  "8315": "Carmen",
  "8316": "Madrid",
  "8317": "Cantillan",
  "8318": "Carrascal",
  "8400": "Surigao City",
  "8401": "San Francisco",
  "8402": "Malimano",
  "8403": "Tagana-an",
  "8404": "Sison",
  "8405": "Placer",
  "8406": "Tubod",
  "8407": "Mainit",
  "8408": "Bacuag",
  "8409": "Gigaquit",
  "8410": "Claver",
  "8411": "Cagdianao",
  "8412": "Dinagat",
  "8413": "Basilisa (Rizal)",
  "8414": "Libjo (Albor)",
  "8415": "Loreto",
  "8416": "Socorro",
  "8417": "Dapa",
  "8418": "Del Carmen",
  "8419": "Gen. Luna",
  "8420": "Pilar",
  "8421": "San Isidro",
  "8422": "Santa Monica",
  "8423": "San Benito",
  "8424": "Burgos",
  "8425": "Alegria",
  "8426": "Tubajon",
  "8427": "San Jose",
  "8500": "Prosperidad",
  "8501": "San Francisco",
  "8502": "Bayugan",
  "8503": "Sibagat",
  "8504": "Rosario",
  "8505": "Trento",
  "8506": "Bunawan",
  "8507": "Loreto",
  "8508": "La Paz",
  "8509": "Veruela",
  "8510": "Talacogon",
  "8511": "San Luis",
  "8512": "Santa Josefa",
  "8513": "Esperanza",
  "8600": "Butuan City",
  "8601": "Buenavista",
  "8602": "Nasipit",
  "8603": "Carmen",
  "8604": "Magallanes",
  "8605": "Cabadbaran",
  "8606": "Tubay",
  "8607": "Jabonga",
  "8608": "Santiago",
  "8609": "Kitcharao",
  "8610": "La Nieves",
  "8611": "Remedios T. Romualdez",
  "8700": "Malaybalay",
  "8701": "Sumilao",
  "8702": "Impasugong",
  "8703": "Manolo Fortich",
  "8704": "Malitbog",
  "8705": "Philips",
  "8706": "Libuna",
  "8707": "Baungon",
  "8708": "Talakag",
  "8709": "Valencia",
  "8710": "Musuan",
  "8711": "San Fernando",
  "8712": "Don Carlos",
  "8713": "Kadingilan",
  "8714": "Maramag",
  "8715": "Quezon",
  "8716": "Kitaotao",
  "8717": "Pangantucan",
  "8718": "Kalilangan",
  "8719": "Dangcagan",
  "8720": "Kibawe",
  "8721": "Damulog",
  "8722": "Lantapan",
  "8723": "Kabanglasan",
  "8800": "Nabunturan",
  "8801": "Montevista",
  "8802": "Mawab",
  "8803": "Compostela",
  "8804": "New Bataan",
  "8805": "Monkayo",
  "8806": "Maco",
  "8807": "Mabini",
  "8808": "Maragusan",
  "8809": "Pantukan",
  "8810": "Laak",
  "9000": "Cagayan de Oro City",
  "9001": "Tagoloan",
  "9002": "Villanueva",
  "9003": "Jasaan",
  "9004": "Claveria",
  "9005": "Balingasag",
  "9006": "Lagonglong",
  "9007": "Salay",
  "9008": "Binuangan",
  "9009": "Sugbongcogon",
  "9010": "Kinogitan",
  "9011": "Balinguan",
  "9012": "Talisayan",
  "9013": "Medina",
  "9014": "Gingoog City",
  "9015": "Magsaysay",
  "9016": "Opol",
  "9017": "El Salvador",
  "9018": "Alubijid",
  "9019": "Laguidingan",
  "9020": "Gitaum",
  "9021": "Libertad",
  "9022": "Initao",
  "9023": "Naawan",
  "9024": "Manticao",
  "9025": "Lugait",
  "9100": "Mambajao",
  "9101": "Mahinog",
  "9102": "Guinsiliban",
  "9103": "Sagay",
  "9104": "Catarman",
  "9200": "Iligan City",
  "9201": "Linamon",
  "9202": "Kauswagan",
  "9203": "Matugao",
  "9204": "Poona Piagapo",
  "9205": "Bacolod",
  "9206": "Maigo",
  "9207": "Kolambugan",
  "9208": "Pantao Ragat",
  "9209": "Tubod",
  "9210": "Baroy",
  "9211": "Lala",
  "9212": "Salvador",
  "9213": "Sapad",
  "9214": "Kapatagan",
  "9215": "Karomatan",
  "9216": "Nunungan",
  "9217": "Baloi",
  "9218": "Pantar",
  "9219": "Munai",
  "9220": "Tangkal",
  "9221": "Magsaysay",
  "9222": "Tagoloan",
  "9300": "Malabang",
  "9302": "Blabagan",
  "9303": [
    "Maragong",
    "Sultan Gumander"
  ],
  "9304": "Tubaran",
  "9305": "Butig",
  "9306": "Lumbayanague",
  "9307": "Lumbatan",
  "9308": "Macador Andong",
  "9309": "Bayang",
  "9310": "Binidayan",
  "9311": "Ganassi",
  "9312": "Pagayawan",
  "9313": "Pualas",
  "9314": "Madamba",
  "9315": "Madalum",
  "9316": "Bacolod Grande",
  "9317": "Tugaya",
  "9318": "Balindong",
  "9319": "Calanogas",
  "9320": "Baumbaran",
  "9321": "Tagoloan II",
  "9400": "Kidapawan",
  "9401": "Makilala",
  "9402": "M'lang",
  "9403": "Tulunan",
  "9404": "Magpet",
  "9405": "Pres. Roxas",
  "9406": "Matalam",
  "9407": "Kabacan",
  "9408": "Carmen",
  "9409": "Pikit",
  "9410": "Midsayap",
  "9411": "Libungan",
  "9412": "Pigkawayan",
  "9413": "Alamada",
  "9414": "Antipas",
  "9415": "Aleosan",
  "9416": "Banisilan",
  "9417": "Arakan",
  "9500": "Gen. Santos City",
  "9501": "Alabel",
  "9502": "Maasim",
  "9503": "Malungon",
  "9504": "Polomolok",
  "9505": "Tupi",
  "9506": "Koronadal",
  "9507": "Tampacan",
  "9508": "Norala",
  "9509": "Santo Nino",
  "9510": "Tantangan",
  "9511": "Banga",
  "9512": "Surallah",
  "9513": "T'boli",
  "9514": "Kiamba",
  "9515": "Maitum",
  "9516": "Malapatan",
  "9517": "Glan",
  "9600": "Cotabato City",
  "9601": "Datu Odin Sinsuat (Dinaig)",
  "9602": "Upi",
  "9603": "South Upi",
  "9604": "Parang",
  "9605": "Sultan Kudarat",
  "9606": "Kabuntulan",
  "9607": "Datu Piang",
  "9608": "Maganoy",
  "9609": "Ampatuan",
  "9610": "Pagalungan",
  "9611": "Sultan Sa Barongis",
  "9612": "Talayan",
  "9613": "Matanog",
  "9614": "Barira",
  "9615": "Buldon",
  "9616": "Buluan",
  "9617": "Datu Paglas",
  "9618": "Gen. S. K. Datun",
  "9700": "Marawi City",
  "9701": "Saguiaran",
  "9702": "Mulondo",
  "9703": "Lumba Bayabao",
  "9704": "Tamparan",
  "9705": "Poona Bayabao",
  "9706": "Masio",
  "9708": "Bubong",
  "9709": "Kapal",
  "9710": "Piagapo",
  "9711": "Marangtao",
  "9712": "Taraka",
  "9713": "Ramain-Ditsaan",
  "9714": "Buadiposo Buntong",
  "9715": "Maguing",
  "9716": "Wao",
  "9800": "Takurong",
  "9801": "Colombio",
  "9802": "Mariano Marcos",
  "9803": "Lutayan",
  "9804": "Pres. Quirino",
  "9805": "Isulan",
  "9806": "Esperanza (Ampatuan)",
  "9807": "Lebak (Salaman)",
  "9808": "Kalamansig",
  "9809": "Palimbang",
  "9810": "Bagumbayan",
  "9811": "Sen. Ninoy Aquino"
}
